py_wechat_tools/__init__.py
py_wechat_tools/libs/__init__.py
py_wechat_tools/libs/tools.py
py_wechat_tools/libs/we_exception.py
py_wechat_tools/mini_program/__init__.py
py_wechat_tools/mini_program/analysis.py
py_wechat_tools/mini_program/auth.py
py_wechat_tools/mini_program/broadcast.py
py_wechat_tools/mini_program/check.py
py_wechat_tools/mini_program/img.py
py_wechat_tools/mini_program/ocr.py
py_wechat_tools/mini_program/risk_control.py
py_wechat_tools/mini_program/security.py
py_wechat_tools/mini_program/shortlink.py
py_wechat_tools/mini_program/soter.py
py_wechat_tools/mini_program/subscribe_message.py
py_wechat_tools/mini_program/uniform_message.py
py_wechat_tools/mini_program/updatable_message.py
py_wechat_tools/official_account/__init__.py
py_wechat_tools/official_account/img.py
py_wechat_tools/official_account/oauth2.py
py_wechat_tools-0.1.0.dist-info/LICENSE
py_wechat_tools-0.1.0.dist-info/METADATA
py_wechat_tools-0.1.0.dist-info/WHEEL
py_wechat_tools-0.1.0.dist-info/top_level.txt
py_wechat_tools-0.1.0.dist-info/RECORD
