Metadata-Version: 2.1
Name: py-wechat-tools
Version: 0.1.0
Summary: 微信小程序/公众号服务端接口集成SDK（非所有接口，持续更新中）
Home-page: https://gitee.com/mjinnn/py-wechat-tools.git
Author: mjinnn
Author-email: 932288652@qq.com
Classifier: Programming Language :: Python :: 3
Classifier: License :: OSI Approved :: MIT License
Classifier: Operating System :: OS Independent
License-File: LICENSE
Requires-Dist: requests >=2.20
Requires-Dist: cacheout >=0.13.1
Requires-Dist: pycryptodome >=3
